Fifty_Docker-1.1.dist-info/METADATA
Fifty_Docker-1.1.dist-info/RECORD
Fifty_Docker-1.1.dist-info/WHEEL
Fifty_Docker-1.1.dist-info/entry_points.txt
Fifty_Docker-1.1.dist-info/top_level.txt
fifty_docker/__init__.py
fifty_docker/main.py
